[
   {
      "id":1,
      "name":"Tom",
      "month":"June",
      "total_cost":120
   },
   {
      "id":1,
      "name":"Tom",
      "month":"June",
      "total_cost":240
   },
   {
      "id":1,
      "name":"Tom",
      "month":"June",
      "total_cost":400
   },
   {
      "id":1,
      "name":"Tom",
      "month":"June",
      "total_cost":12
   },
   {
      "id":2,
      "name":"Bond",
      "month":"June",
      "total_cost":120
   },
   {
      "id":2,
      "name":"Bond",
      "month":"June",
      "total_cost":140
   },
   {
      "id":2,
      "name":"Bond",
      "month":"June",
      "total_cost":320
   },
   {
      "id":2,
      "name":"Bond",
      "month":"June",
      "total_cost":12
   }
]